{
  "name": "Campo Largo",
  "indices": {
    "CDD": {
      "historical": {
        "baseline": {
          "period": "1980-2005",
          "value": 15.38
        },
        "timeseriesStart": 1961,
        "timeseriesEnd": 2005
      },
      "projections": {
        "rcp45": null,
        "rcp85": null
      }
    },
    "RX1day": {
      "historical": {
        "baseline": {
          "period": "1980-2005",
          "value": 51.84
        },
        "timeseriesStart": 1961,
        "timeseriesEnd": 2005
      },
      "projections": {
        "rcp45": null,
        "rcp85": null
      }
    },
    "RX5day": {
      "historical": {
        "baseline": {
          "period": "1980-2005",
          "value": 113.61
        },
        "timeseriesStart": 1961,
        "timeseriesEnd": 2005
      },
      "projections": {
        "rcp45": null,
        "rcp85": null
      }
    },
    "TX90p": {
      "historical": {
        "baseline": {
          "period": "1980-2005",
          "value": 9.31
        },
        "timeseriesStart": 1961,
        "timeseriesEnd": 2005
      },
      "projections": {
        "rcp45": null,
        "rcp85": null
      }
    },
    "tas": {
      "historical": {
        "baseline": {
          "period": "1980-2005",
          "value": 18.07
        },
        "timeseriesStart": 1961,
        "timeseriesEnd": 2005
      },
      "projections": {
        "rcp45": null,
        "rcp85": null
      }
    },
    "tasmax": {
      "historical": {
        "baseline": {
          "period": "1980-2005",
          "value": 23.45
        },
        "timeseriesStart": 1961,
        "timeseriesEnd": 2005
      },
      "projections": {
        "rcp45": null,
        "rcp85": null
      }
    }
  }
}